tests/__init__.py
tests/test_transformer.py
xgboost_data_transformer/__init__.py
xgboost_data_transformer/transformer.py
xgboost_data_transformer-0.1.0.dist-info/METADATA
xgboost_data_transformer-0.1.0.dist-info/WHEEL
xgboost_data_transformer-0.1.0.dist-info/top_level.txt
xgboost_data_transformer-0.1.0.dist-info/RECORD
