Metadata-Version: 2.1
Name: xgboost_data_transformer
Version: 0.1.0
Summary: A package for transforming raw data for XGBoost.
Home-page: https://github.com/noorains/xgboost_data_transformer
Author: Noorain Kazmi
Author-email: noosykaz@gmail.com
Classifier: Programming Language :: Python :: 3
Classifier: License :: OSI Approved :: MIT License
Classifier: Operating System :: OS Independent
Requires-Python: >=3.6
Requires-Dist: pandas >=1.0.0
